pytest_fixture_forms/CustomModule.py
pytest_fixture_forms/FixtureForms.py
pytest_fixture_forms/__init__.py
pytest_fixture_forms/helpers.py
pytest_fixture_forms/hooks.py
pytest_fixture_forms/newhooks.py
pytest_fixture_forms/plugin.py
pytest_fixture_forms/utils.py
pytest_fixture_forms-0.2.1.dist-info/LICENSE
pytest_fixture_forms-0.2.1.dist-info/METADATA
pytest_fixture_forms-0.2.1.dist-info/WHEEL
pytest_fixture_forms-0.2.1.dist-info/entry_points.txt
pytest_fixture_forms-0.2.1.dist-info/top_level.txt
pytest_fixture_forms-0.2.1.dist-info/RECORD
