Metadata-Version: 2.1
Name: pytest-fixture-forms
Version: 0.2.1
Summary: A pytest plugin for creating fixtures that holds different forms between tests.
Author-email: eliav2 <louski.a@gmail.com>
Project-URL: Homepage, https://github.com/Eliav2/pytest-fixture-forms
Classifier: Framework :: Pytest
Classifier: Programming Language :: Python :: 3.10
Classifier: Programming Language :: Python :: 3.11
Classifier: Programming Language :: Python :: 3.12
Requires-Python: >=3.10
License-File: LICENSE
Requires-Dist: ordered-set>=4.1.0
Requires-Dist: pytest<9.0.0,>=7.0.0
Provides-Extra: dev
Requires-Dist: ruff; extra == "dev"
Requires-Dist: tox; extra == "dev"
Requires-Dist: pytest-xdist; extra == "dev"
